Workbook

Sheet Inputs
B1: SDG&E (EV-TOU-5) — Input Parameters
B2: Blue = editable | Black = formula | Green = cross-sheet link
B4: SYSTEM PARAMETERS
B5: PV + Storage System Cost | C5: 32031.5 | E5: Solar $17,303 + Battery $14,728
B6: Solar Only System Cost | C6: 17303 | E6: Tao Sun et al. (2025), CA: $2860/kW
B7: Solar PV Capacity | C7: 6.05 | D7: kW
B8: Battery Storage Capacity | C8: 13.5 | D8: kWh
B10: FINANCIAL PARAMETERS
B11: Debt Interest Rate | C11: 0.0724
B12: Customer Discount Rate | C12: 0.064
B13: Loan Term | C13: 25 | D13: years
B14: Electricity Cost Escalation Rate | C14: 0.025
B16: INCENTIVES
B17: Federal ITC Rate | C17: 0 | E17: Expired Dec 2025; set to 0%
B18: FedITC Amount — PV+Storage | C18: =C5*C17
B19: FedITC Amount — Solar Only | C19: =C6*C17
B20: State Battery Incentive (SGIP) | C20: 0 | E20: SGIP closed Dec 2025; $0
B22: YEAR 1 ELECTRICITY BILLS (from PySAM)
C23: Without System | D23: With System | E23: Annual Savings
B25: SDG&E — Solar Only (EV-TOU-5) | C25: 3226.29 | D25: 1907.79 | E25: =C25-D25
B26: SDG&E — PV+Storage (EV-TOU-5) | C26: 3226.29 | D26: 807.38 | E26: =C26-D26
B28: PV PRODUCTION (from PySAM)
B29: San Diego Annual PV kWh | C29: 10239
B30: San Diego Annual Load kWh | C30: 7220

Sheet Solar Only
A1: SDG&E - Solar Only (EV-TOU-5)
A2: All formulas reference Inputs sheet. No incentives (Phase A).
A4: No Incentives (ITC=0%, SGIP=$0)
A5: Year | B5: 0 | C5: 1 | D5: 2 | E5: 3 | F5: 4 | G5: 5 | H5: 6 | I5: 7 | J5: 8 | K5: 9 | L5: 10 | M5: 11 | N5: 12 | O5: 13 | P5: 14 | Q5: 15 | R5: 16 | S5: 17 | T5: 18 | U5: 19 | V5: 20 | W5: 21 | X5: 22 | Y5: 23 | Z5: 24 | AA5: 25 | AB5: 25yr Total | AC5: 25yr NPV
A6: Debt Balance ($) | B6: =Inputs!C6 | C6: =MAX(0,B6-C8) | D6: =MAX(0,C6-D8) | E6: =MAX(0,D6-E8) | F6: =MAX(0,E6-F8) | G6: =MAX(0,F6-G8) | H6: =MAX(0,G6-H8) | I6: =MAX(0,H6-I8) | J6: =MAX(0,I6-J8) | ... AA6: =MAX(0,Z6-AA8)
A7: Interest Payment ($) | B7: 0 | C7: =IF(B6<=0,0,B6*Inputs!$C$11) | D7: =IF(C6<=0,0,C6*Inputs!$C$11) | E7: =IF(D6<=0,0,D6*Inputs!$C$11) | F7: =IF(E6<=0,0,E6*Inputs!$C$11) | G7: =IF(F6<=0,0,F6*Inputs!$C$11) | H7: =IF(G6<=0,0,G6*Inputs!$C$11) | I7: =IF(H6<=0,0,H6*Inputs!$C$11) | J7: =IF(I6<=0,0,I6*Inputs!$C$11) | ... AA7: =IF(Z6<=0,0,Z6*Inputs!$C$11)
A8: Principal Payment ($) | B8: 0 | C8: =IF(B6<=0,0,C9-C7) | D8: =IF(B6<=0,0,D9-D7) | E8: =IF(B6<=0,0,E9-E7) | F8: =IF(B6<=0,0,F9-F7) | G8: =IF(B6<=0,0,G9-G7) | H8: =IF(B6<=0,0,H9-H7) | I8: =IF(B6<=0,0,I9-I7) | J8: =IF(B6<=0,0,J9-J7) | K8: =IF(B6<=0,0,K9-K7) | L8: =IF(B6<=0,0,L9-L7) | M8: =IF(B6<=0,0,M9-M7) | N8: =IF(B6<=0,0,N9-N7) | O8: =IF(B6<=0,0,O9-O7) | P8: =IF(B6<=0,0,P9-P7) | Q8: =IF(B6<=0,0,Q9-Q7) | R8: =IF(B6<=0,0,R9-R7) | S8: =IF(B6<=0,0,S9-S7) | T8: =IF(B6<=0,0,T9-T7) | U8: =IF(B6<=0,0,U9-U7) | V8: =IF(B6<=0,0,V9-V7) | W8: =IF(B6<=0,0,W9-W7) | X8: =IF(B6<=0,0,X9-X7) | Y8: =IF(B6<=0,0,Y9-Y7) | Z8: =IF(B6<=0,0,Z9-Z7) | AA8: =IF(B6<=0,0,AA9-AA7)
A9: Total Payment - P&I ($) | B9: 0 | C9: =IF(B6<=0,0,ABS(PMT(Inputs!$C$11,Inputs!$C$13,B6,0))) | D9: =IF(B6<=0,0,ABS(PMT(Inputs!$C$11,Inputs!$C$13,B6,0))) | E9: =IF(B6<=0,0,ABS(PMT(Inputs!$C$11,Inputs!$C$13,B6,0))) | F9: =IF(B6<=0,0,ABS(PMT(Inputs!$C$11,Inputs!$C$13,B6,0))) | G9: =IF(B6<=0,0,ABS(PMT(Inputs!$C$11,Inputs!$C$13,B6,0))) | H9: =IF(B6<=0,0,ABS(PMT(Inputs!$C$11,Inputs!$C$13,B6,0))) | I9: =IF(B6<=0,0,ABS(PMT(Inputs!$C$11,Inputs!$C$13,B6,0))) | J9: =IF(B6<=0,0,ABS(PMT(Inputs!$C$11,Inputs!$C$13,B6,0))) | K9: =IF(B6<=0,0,ABS(PMT(Inputs!$C$11,Inputs!$C$13,B6,0))) | L9: =IF(B6<=0,0,ABS(PMT(Inputs!$C$11,Inputs!$C$13,B6,0))) | M9: =IF(B6<=0,0,ABS(PMT(Inputs!$C$11,Inputs!$C$13,B6,0))) | N9: =IF(B6<=0,0,ABS(PMT(Inputs!$C$11,Inputs!$C$13,B6,0))) | O9: =IF(B6<=0,0,ABS(PMT(Inputs!$C$11,Inputs!$C$13,B6,0))) | P9: =IF(B6<=0,0,ABS(PMT(Inputs!$C$11,Inputs!$C$13,B6,0))) | Q9: =IF(B6<=0,0,ABS(PMT(Inputs!$C$11,Inputs!$C$13,B6,0))) | R9: =IF(B6<=0,0,ABS(PMT(Inputs!$C$11,Inputs!$C$13,B6,0))) | S9: =IF(B6<=0,0,ABS(PMT(Inputs!$C$11,Inputs!$C$13,B6,0))) | T9: =IF(B6<=0,0,ABS(PMT(Inputs!$C$11,Inputs!$C$13,B6,0))) | U9: =IF(B6<=0,0,ABS(PMT(Inputs!$C$11,Inputs!$C$13,B6,0))) | V9: =IF(B6<=0,0,ABS(PMT(Inputs!$C$11,Inputs!$C$13,B6,0))) | W9: =IF(B6<=0,0,ABS(PMT(Inputs!$C$11,Inputs!$C$13,B6,0))) | X9: =IF(B6<=0,0,ABS(PMT(Inputs!$C$11,Inputs!$C$13,B6,0))) | Y9: =IF(B6<=0,0,ABS(PMT(Inputs!$C$11,Inputs!$C$13,B6,0))) | Z9: =IF(B6<=0,0,ABS(PMT(Inputs!$C$11,Inputs!$C$13,B6,0))) | AA9: =IF(B6<=0,0,ABS(PMT(Inputs!$C$11,Inputs!$C$13,B6,0))) | AB9: =SUM(C9:AA9) | AC9: =NPV(Inputs!$C$12,C9:AA9)
A11: Elec. Bill - No System ($) | B11: 0 | C11: =Inputs!C25 | D11: =C11*(1+Inputs!$C$14) | E11: =D11*(1+Inputs!$C$14) | F11: =E11*(1+Inputs!$C$14) | G11: =F11*(1+Inputs!$C$14) | H11: =G11*(1+Inputs!$C$14) | I11: =H11*(1+Inputs!$C$14) | J11: =I11*(1+Inputs!$C$14) | K11: =J11*(1+Inputs!$C$14) | ... AA11: =Z11*(1+Inputs!$C$14)
A12: Elec. Bill - With System ($) | B12: 0 | C12: =Inputs!D25 | D12: =C12*(1+Inputs!$C$14) | E12: =D12*(1+Inputs!$C$14) | F12: =E12*(1+Inputs!$C$14) | G12: =F12*(1+Inputs!$C$14) | H12: =G12*(1+Inputs!$C$14) | I12: =H12*(1+Inputs!$C$14) | J12: =I12*(1+Inputs!$C$14) | K12: =J12*(1+Inputs!$C$14) | ... AA12: =Z12*(1+Inputs!$C$14)
A13: Bill Savings ($) | B13: 0 | C13: =C11-C12 | D13: =D11-D12 | E13: =E11-E12 | F13: =F11-F12 | G13: =G11-G12 | H13: =H11-H12 | I13: =I11-I12 | J13: =J11-J12 | ... AA13: =AA11-AA12 | AB13: =SUM(C13:AA13) | AC13: =NPV(Inputs!$C$12,C13:AA13)
A14: Net Savings ($) | B14: =B13-B9 | C14: =C13-C9 | D14: =D13-D9 | E14: =E13-E9 | F14: =F13-F9 | G14: =G13-G9 | H14: =H13-H9 | I14: =I13-I9 | ... AA14: =AA13-AA9 | AB14: =SUM(C14:AA14) | AC14: =NPV(Inputs!$C$12,C14:AA14)

Sheet PV+Storage
A1: SDG&E - PV+Storage (EV-TOU-5)
A2: All formulas reference Inputs sheet. No incentives (Phase A).
A4: No Incentives (ITC=0%, SGIP=$0)
A5: Year | B5: 0 | C5: 1 | D5: 2 | E5: 3 | F5: 4 | G5: 5 | H5: 6 | I5: 7 | J5: 8 | K5: 9 | L5: 10 | M5: 11 | N5: 12 | O5: 13 | P5: 14 | Q5: 15 | R5: 16 | S5: 17 | T5: 18 | U5: 19 | V5: 20 | W5: 21 | X5: 22 | Y5: 23 | Z5: 24 | AA5: 25 | AB5: 25yr Total | AC5: 25yr NPV
A6: Debt Balance ($) | B6: =Inputs!C5 | C6: =MAX(0,B6-C8) | D6: =MAX(0,C6-D8) | E6: =MAX(0,D6-E8) | F6: =MAX(0,E6-F8) | G6: =MAX(0,F6-G8) | H6: =MAX(0,G6-H8) | I6: =MAX(0,H6-I8) | J6: =MAX(0,I6-J8) | ... AA6: =MAX(0,Z6-AA8)
A7: Interest Payment ($) | B7: 0 | C7: =IF(B6<=0,0,B6*Inputs!$C$11) | D7: =IF(C6<=0,0,C6*Inputs!$C$11) | E7: =IF(D6<=0,0,D6*Inputs!$C$11) | F7: =IF(E6<=0,0,E6*Inputs!$C$11) | G7: =IF(F6<=0,0,F6*Inputs!$C$11) | H7: =IF(G6<=0,0,G6*Inputs!$C$11) | I7: =IF(H6<=0,0,H6*Inputs!$C$11) | J7: =IF(I6<=0,0,I6*Inputs!$C$11) | ... AA7: =IF(Z6<=0,0,Z6*Inputs!$C$11)
A8: Principal Payment ($) | B8: 0 | C8: =IF(B6<=0,0,C9-C7) | D8: =IF(B6<=0,0,D9-D7) | E8: =IF(B6<=0,0,E9-E7) | F8: =IF(B6<=0,0,F9-F7) | G8: =IF(B6<=0,0,G9-G7) | H8: =IF(B6<=0,0,H9-H7) | I8: =IF(B6<=0,0,I9-I7) | J8: =IF(B6<=0,0,J9-J7) | K8: =IF(B6<=0,0,K9-K7) | L8: =IF(B6<=0,0,L9-L7) | M8: =IF(B6<=0,0,M9-M7) | N8: =IF(B6<=0,0,N9-N7) | O8: =IF(B6<=0,0,O9-O7) | P8: =IF(B6<=0,0,P9-P7) | Q8: =IF(B6<=0,0,Q9-Q7) | R8: =IF(B6<=0,0,R9-R7) | S8: =IF(B6<=0,0,S9-S7) | T8: =IF(B6<=0,0,T9-T7) | U8: =IF(B6<=0,0,U9-U7) | V8: =IF(B6<=0,0,V9-V7) | W8: =IF(B6<=0,0,W9-W7) | X8: =IF(B6<=0,0,X9-X7) | Y8: =IF(B6<=0,0,Y9-Y7) | Z8: =IF(B6<=0,0,Z9-Z7) | AA8: =IF(B6<=0,0,AA9-AA7)
A9: Total Payment - P&I ($) | B9: 0 | C9: =IF(B6<=0,0,ABS(PMT(Inputs!$C$11,Inputs!$C$13,B6,0))) | D9: =IF(B6<=0,0,ABS(PMT(Inputs!$C$11,Inputs!$C$13,B6,0))) | E9: =IF(B6<=0,0,ABS(PMT(Inputs!$C$11,Inputs!$C$13,B6,0))) | F9: =IF(B6<=0,0,ABS(PMT(Inputs!$C$11,Inputs!$C$13,B6,0))) | G9: =IF(B6<=0,0,ABS(PMT(Inputs!$C$11,Inputs!$C$13,B6,0))) | H9: =IF(B6<=0,0,ABS(PMT(Inputs!$C$11,Inputs!$C$13,B6,0))) | I9: =IF(B6<=0,0,ABS(PMT(Inputs!$C$11,Inputs!$C$13,B6,0))) | J9: =IF(B6<=0,0,ABS(PMT(Inputs!$C$11,Inputs!$C$13,B6,0))) | K9: =IF(B6<=0,0,ABS(PMT(Inputs!$C$11,Inputs!$C$13,B6,0))) | L9: =IF(B6<=0,0,ABS(PMT(Inputs!$C$11,Inputs!$C$13,B6,0))) | M9: =IF(B6<=0,0,ABS(PMT(Inputs!$C$11,Inputs!$C$13,B6,0))) | N9: =IF(B6<=0,0,ABS(PMT(Inputs!$C$11,Inputs!$C$13,B6,0))) | O9: =IF(B6<=0,0,ABS(PMT(Inputs!$C$11,Inputs!$C$13,B6,0))) | P9: =IF(B6<=0,0,ABS(PMT(Inputs!$C$11,Inputs!$C$13,B6,0))) | Q9: =IF(B6<=0,0,ABS(PMT(Inputs!$C$11,Inputs!$C$13,B6,0))) | R9: =IF(B6<=0,0,ABS(PMT(Inputs!$C$11,Inputs!$C$13,B6,0))) | S9: =IF(B6<=0,0,ABS(PMT(Inputs!$C$11,Inputs!$C$13,B6,0))) | T9: =IF(B6<=0,0,ABS(PMT(Inputs!$C$11,Inputs!$C$13,B6,0))) | U9: =IF(B6<=0,0,ABS(PMT(Inputs!$C$11,Inputs!$C$13,B6,0))) | V9: =IF(B6<=0,0,ABS(PMT(Inputs!$C$11,Inputs!$C$13,B6,0))) | W9: =IF(B6<=0,0,ABS(PMT(Inputs!$C$11,Inputs!$C$13,B6,0))) | X9: =IF(B6<=0,0,ABS(PMT(Inputs!$C$11,Inputs!$C$13,B6,0))) | Y9: =IF(B6<=0,0,ABS(PMT(Inputs!$C$11,Inputs!$C$13,B6,0))) | Z9: =IF(B6<=0,0,ABS(PMT(Inputs!$C$11,Inputs!$C$13,B6,0))) | AA9: =IF(B6<=0,0,ABS(PMT(Inputs!$C$11,Inputs!$C$13,B6,0))) | AB9: =SUM(C9:AA9) | AC9: =NPV(Inputs!$C$12,C9:AA9)
A11: Elec. Bill - No System ($) | B11: 0 | C11: =Inputs!C26 | D11: =C11*(1+Inputs!$C$14) | E11: =D11*(1+Inputs!$C$14) | F11: =E11*(1+Inputs!$C$14) | G11: =F11*(1+Inputs!$C$14) | H11: =G11*(1+Inputs!$C$14) | I11: =H11*(1+Inputs!$C$14) | J11: =I11*(1+Inputs!$C$14) | K11: =J11*(1+Inputs!$C$14) | ... AA11: =Z11*(1+Inputs!$C$14)
A12: Elec. Bill - With System ($) | B12: 0 | C12: =Inputs!D26 | D12: =C12*(1+Inputs!$C$14) | E12: =D12*(1+Inputs!$C$14) | F12: =E12*(1+Inputs!$C$14) | G12: =F12*(1+Inputs!$C$14) | H12: =G12*(1+Inputs!$C$14) | I12: =H12*(1+Inputs!$C$14) | J12: =I12*(1+Inputs!$C$14) | K12: =J12*(1+Inputs!$C$14) | ... AA12: =Z12*(1+Inputs!$C$14)
A13: Bill Savings ($) | B13: 0 | C13: =C11-C12 | D13: =D11-D12 | E13: =E11-E12 | F13: =F11-F12 | G13: =G11-G12 | H13: =H11-H12 | I13: =I11-I12 | J13: =J11-J12 | ... AA13: =AA11-AA12 | AB13: =SUM(C13:AA13) | AC13: =NPV(Inputs!$C$12,C13:AA13)
A14: Net Savings ($) | B14: =B13-B9 | C14: =C13-C9 | D14: =D13-D9 | E14: =E13-E9 | F14: =F13-F9 | G14: =G13-G9 | H14: =H13-H9 | I14: =I13-I9 | ... AA14: =AA13-AA9 | AB14: =SUM(C14:AA14) | AC14: =NPV(Inputs!$C$12,C14:AA14)

Sheet Summary
A1: SDG&E (EV-TOU-5) - Summary (No Incentives)
A3: System | B3: System Cost | C3: Y1 Savings | D3: PMT | E3: Monthly Net | F3: 25yr NPV
A4: Solar Only | B4: =Inputs!C6 | C4: ='Solar Only'!C14+'Solar Only'!C13 | D4: ='Solar Only'!C13-'Solar Only'!C14 | E4: ='Solar Only'!C14/12 | F4: ='Solar Only'!AC14
A5: PV+Storage | B5: =Inputs!C5 | C5: ='PV+Storage'!C14+'PV+Storage'!C13 | D5: ='PV+Storage'!C13-'PV+Storage'!C14 | E5: ='PV+Storage'!C14/12 | F5: ='PV+Storage'!AC14
A7: Battery Delta | B7: =B5-B4 | C7: =C5-C4 | E7: =E5-E4 | F7: =F5-F4
